gym_bhsl/__init__.py
gym_bhsl/envs/__init__.py
gym_bhsl/envs/bhsl_env.py
gym_bhsl/math/__init__.py
gym_bhsl/math/average.py
gym_bhsl/math/noise.py
tests/__init__.py
tests/test_bhsl.py
tests/test_math.py
tests/test_noise.py
gym_buy_high_sell_low-0.2.1.dist-info/LICENSE
gym_buy_high_sell_low-0.2.1.dist-info/METADATA
gym_buy_high_sell_low-0.2.1.dist-info/WHEEL
gym_buy_high_sell_low-0.2.1.dist-info/top_level.txt
gym_buy_high_sell_low-0.2.1.dist-info/RECORD
