Metadata-Version: 2.1
Name: gym-buy-high-sell-low
Version: 0.2.1
Summary: An OpenAI Gym stock market environment
Home-page: https://github.com/tjkemp/gym-buy-high-sell-low
Author: tjkemp
Author-email: tero.kemppi@gmail.com
License: UNKNOWN
Project-URL: Bug Tracker, https://github.com/tpjkemp/gym-buy-high-sell-low/issues
Keywords: gym environment,reinforcement learning
Platform: UNKNOWN
Classifier: Programming Language :: Python :: 3.9
Classifier: Programming Language :: Python :: 3.8
Classifier: Programming Language :: Python :: 3.7
Classifier: License :: OSI Approved :: MIT License
Classifier: Operating System :: OS Independent
Classifier: Development Status :: 4 - Beta
Requires-Python: >=3.7
License-File: LICENSE
Requires-Dist: gym
Requires-Dist: numpy
